oxapi/__init__.py
oxapi/asynch.py
oxapi/config.py
oxapi/error.py
oxapi/utils.py
oxapi/abstract/__init__.py
oxapi/abstract/api.py
oxapi/nlp/__init__.py
oxapi/nlp/classification.py
oxapi/nlp/completion.py
oxapi/nlp/encoding.py
oxapi/nlp/pipeline.py
oxapi/nlp/transformation.py
oxapi-1.1.3.dist-info/LICENSE
oxapi-1.1.3.dist-info/METADATA
oxapi-1.1.3.dist-info/WHEEL
oxapi-1.1.3.dist-info/top_level.txt
oxapi-1.1.3.dist-info/RECORD
