Metadata-Version: 2.1
Name: oxapi
Version: 1.1.3
Summary: The Python library for querying the OxAPI
Author: Oxolo GmbH
Author-email: support@oxapi.ai
Project-URL: Source Code, https://github.com/Oxolo/oxapi-python
License-File: LICENSE
Requires-Dist: grequests (>=0.6.0)
Requires-Dist: numpy (>=1.17)
Requires-Dist: pandas (>=1.3)
Requires-Dist: requests (>=2.27)
Requires-Dist: urllib3 (>=1.26.5)
Requires-Dist: jinja2 (>=2.11.3)
Requires-Dist: hypothesis (>=6.54.3)
Requires-Dist: jedi (>=0.10)
